odoo8_addon_account_vat_period_end_statement-8.0.3.0.1-nspkg.pth
odoo_addons/account_vat_period_end_statement/README.rst
odoo_addons/account_vat_period_end_statement/__init__.py
odoo_addons/account_vat_period_end_statement/__openerp__.py
odoo_addons/account_vat_period_end_statement/reports.xml
odoo_addons/account_vat_period_end_statement/statement_workflow.xml
odoo_addons/account_vat_period_end_statement/i18n/account_vat_period_end_statement.pot
odoo_addons/account_vat_period_end_statement/i18n/es.po
odoo_addons/account_vat_period_end_statement/i18n/it.po
odoo_addons/account_vat_period_end_statement/i18n/sl.po
odoo_addons/account_vat_period_end_statement/migrations/8.0.3.0.0/post-migration.py
odoo_addons/account_vat_period_end_statement/models/__init__.py
odoo_addons/account_vat_period_end_statement/models/account.py
odoo_addons/account_vat_period_end_statement/models/config.py
odoo_addons/account_vat_period_end_statement/report/__init__.py
odoo_addons/account_vat_period_end_statement/report/vat_period_end_statement.py
odoo_addons/account_vat_period_end_statement/security/ir.model.access.csv
odoo_addons/account_vat_period_end_statement/security/security.xml
odoo_addons/account_vat_period_end_statement/static/description/icon.png
odoo_addons/account_vat_period_end_statement/static/src/css/l10n_it_vat_registries.css
odoo_addons/account_vat_period_end_statement/tests/__init__.py
odoo_addons/account_vat_period_end_statement/tests/test_vat_statement.py
odoo_addons/account_vat_period_end_statement/views/account_view.xml
odoo_addons/account_vat_period_end_statement/views/config.xml
odoo_addons/account_vat_period_end_statement/views/report_vatperiodendstatement.xml
odoo_addons/account_vat_period_end_statement/wizard/__init__.py
odoo_addons/account_vat_period_end_statement/wizard/add_period.py
odoo_addons/account_vat_period_end_statement/wizard/add_period.xml
odoo_addons/account_vat_period_end_statement/wizard/remove_period.py
odoo8_addon_account_vat_period_end_statement-8.0.3.0.1.dist-info/METADATA
odoo8_addon_account_vat_period_end_statement-8.0.3.0.1.dist-info/WHEEL
odoo8_addon_account_vat_period_end_statement-8.0.3.0.1.dist-info/namespace_packages.txt
odoo8_addon_account_vat_period_end_statement-8.0.3.0.1.dist-info/top_level.txt
odoo8_addon_account_vat_period_end_statement-8.0.3.0.1.dist-info/RECORD
